takemeto/__init__.py
takemeto/local_storage.py
takemeto/main.py
takemeto-0.1.4.dist-info/entry_points.txt
takemeto-0.1.4.dist-info/LICENSE
takemeto-0.1.4.dist-info/WHEEL
takemeto-0.1.4.dist-info/METADATA
takemeto-0.1.4.dist-info/RECORD
